geneinfo/__init__.py
geneinfo/cli.py
geneinfo/core.py
geneinfo/mock_data.py
geneinfo/utils.py
geneinfo/fetchers/__init__.py
geneinfo/fetchers/base.py
geneinfo/fetchers/clinical.py
geneinfo/fetchers/functional.py
geneinfo/fetchers/genomic.py
geneinfo/fetchers/protein.py
genesummary-0.3.2.dist-info/METADATA
genesummary-0.3.2.dist-info/WHEEL
genesummary-0.3.2.dist-info/entry_points.txt
genesummary-0.3.2.dist-info/licenses/LICENSE
genesummary-0.3.2.dist-info/RECORD
