Metadata-Version: 2.4
Name: genesummary
Version: 0.3.2
Summary: A comprehensive Python package for retrieving detailed gene information from multiple public databases
Project-URL: Homepage, https://chunjie-sam-liu.github.io/geneinfo
Project-URL: Documentation, https://chunjie-sam-liu.github.io/geneinfo
Project-URL: Repository, https://github.com/chunjie-sam-liu/geneinfo
Project-URL: Issues, https://github.com/chunjie-sam-liu/geneinfo/issues
Project-URL: Changelog, https://github.com/chunjie-sam-liu/geneinfo/releases
Author-email: Chunjie Liu <chunjie.sam.liu@gmail.com>
Maintainer-email: Chunjie Liu <chunjie.sam.liu@gmail.com>
License: MIT License
License-File: LICENSE
Keywords: bioinformatics,biology,gene-annotation,genetics,genomics,gwas,pathways,protein
Classifier: Development Status :: 4 - Beta
Classifier: Intended Audience :: Science/Research
Classifier: License :: OSI Approved :: MIT License
Classifier: Operating System :: OS Independent
Classifier: Programming Language :: Python :: 3
Classifier: Programming Language :: Python :: 3.11
Classifier: Programming Language :: Python :: 3.12
Classifier: Topic :: Scientific/Engineering :: Bio-Informatics
Classifier: Topic :: Software Development :: Libraries :: Python Modules
Requires-Python: >=3.11
Requires-Dist: biopython>=1.78
Requires-Dist: click>=8.2.1
Requires-Dist: mygene>=3.2.0
Requires-Dist: numpy>=1.20.0
Requires-Dist: pandas>=1.2.0
Requires-Dist: python-dotenv>=1.0.0
Requires-Dist: requests>=2.25.0
Requires-Dist: rich>=10.0.0
Requires-Dist: typer>=0.9.0
Requires-Dist: urllib3>=1.26.0
